MikPisula-packet-simulator/__init__.py
MikPisula-packet-simulator/__main__.py
MikPisula-packet-simulator/firewall.py
MikPisula-packet-simulator/packet.py
MikPisula-packet-simulator/router.py
MikPisula-packet-simulator/simulator.py
MikPisula-packet-simulator/test_1_pia.py
MikPisula-packet-simulator/docs/libnftables-json(5).txt
MikPisula-packet-simulator/docs/nft(8).txt
firewall_test/__init__.py
firewall_test/__main__.py
firewall_test/ci.py
firewall_test/shell.py
firewall_testing_framework-0.0.1.dist-info/licenses/LICENSE
firewall_testing_framework-0.0.1.dist-info/METADATA
firewall_testing_framework-0.0.1.dist-info/WHEEL
firewall_testing_framework-0.0.1.dist-info/entry_points.txt
firewall_testing_framework-0.0.1.dist-info/top_level.txt
firewall_testing_framework-0.0.1.dist-info/RECORD
